{"nodes": [{"id": "21 - 24", "type": "file", "name": "/usr/home/eve/hello_2", "chg": "none"}, {"id": "9 - 13", "type": "proc", "name": "/usr/bin/ld", "chg": "none"}, {"id": " - 14", "type": "file", "name": "/tmp/hello_2-84c0ca.o", "chg": "add"}, {"id": "6 - 10", "type": "proc", "name": "/usr/bin/cc", "chg": "none"}, {"id": " - 12", "type": "file", "name": "/tmp/hello_2-84c0ca.o-cdcea12d", "chg": "add"}, {"id": "4 - 3", "type": "proc", "name": "/usr/local/bin/bash", "chg": "none"}, {"id": "2 - 2", "type": "proc", "name": "/usr/sbin/sshd", "chg": "none"}, {"id": "1 - 1", "type": "proc", "name": "sshd", "chg": "none"}, {"id": "7 - 11", "type": "file", "name": "/usr/home/eve/hello_2.c", "chg": "none"}, {"id": "8 - ", "type": "file", "name": "/tmp/hello_2-8ee216.o-d71fd4e4", "chg": "del"}, {"id": "3 - 6", "type": "file", "name": "192.168.1.1", "chg": "none"}, {"id": " - 8", "type": "proc", "name": "/bin/cp", "chg": "add"}, {"id": " - 5", "type": "file", "name": "/usr/home/bob/crt1.o", "chg": "add"}, {"id": " - 4", "type": "proc", "name": "/usr/bin/scp", "chg": "add"}, {"id": " - 7", "type": "proc", "name": "/usr/local/bin/sudo", "chg": "add"}, {"id": "10 - 15", "type": "file", "name": "/usr/lib/libgcc.a", "chg": "none"}, {"id": "11 - 16", "type": "file", "name": "/usr/lib/libc_nonshared.a", "chg": "none"}, {"id": "12 - 17", "type": "file", "name": "/usr/lib/crtbegin.o", "chg": "none"}, {"id": "13 - 18", "type": "file", "name": "/usr/lib/libc.so", "chg": "none"}, {"id": "14 - 19", "type": "file", "name": "/usr/lib/libssp_nonshared.a", "chg": "none"}, {"id": "5 - ", "type": "file", "name": "/home/eve/.login_conf", "chg": "del"}, {"id": "15 - 9", "type": "file", "name": "/usr/lib/crt1.o", "chg": "none"}, {"id": "16 - 20", "type": "file", "name": "/usr/lib/crti.o", "chg": "none"}, {"id": "17 - ", "type": "file", "name": "/tmp/hello_2-8ee216.o", "chg": "del"}, {"id": "18 - 21", "type": "file", "name": "/usr/lib/crtend.o", "chg": "none"}, {"id": "19 - 22", "type": "file", "name": "/usr/lib/libgcc_s.so", "chg": "none"}, {"id": "20 - 23", "type": "file", "name": "/usr/lib/crtn.o", "chg": "none"}, {"id": "3 - 6", "type": "file", "name": "192.168.1.1", "chg": "none"}, {"id": "9 - 13", "type": "proc", "name": "/usr/bin/ld", "chg": "none"}], "edges": [{"dest": "2 - 2", "src": "1 - 1", "type": "parent", "chg": "none"}, {"dest": "3 - 6", "src": "2 - 2", "type": "rw", "chg": "none"}, {"dest": "4 - 3", "src": "2 - 2", "type": "parent", "chg": "none"}, {"dest": "4 - 3", "src": "5 - ", "type": "r", "chg": "del"}, {"dest": "3 - 6", "src": "4 - 3", "type": "rw", "chg": "none"}, {"dest": "6 - 10", "src": "4 - 3", "type": "parent", "chg": "none"}, {"dest": "6 - 10", "src": "5 - ", "type": "r", "chg": "del"}, {"dest": "3 - 6", "src": "6 - 10", "type": "rw", "chg": "none"}, {"dest": "6 - 10", "src": "6 - 10", "type": "parent", "chg": "none"}, {"dest": "6 - 10", "src": "7 - 11", "type": "r", "chg": "none"}, {"dest": "6 - 10", "src": "5 - ", "type": "r", "chg": "del"}, {"dest": "8 - ", "src": "6 - 10", "type": "w", "chg": "del"}, {"dest": "8 - ", "src": "6 - 10", "type": "rw", "chg": "del"}, {"dest": "3 - 6", "src": "6 - 10", "type": "rw", "chg": "none"}, {"dest": "9 - 13", "src": "6 - 10", "type": "parent", "chg": "none"}, {"dest": "9 - 13", "src": "10 - 15", "type": "r", "chg": "none"}, {"dest": "9 - 13", "src": "11 - 16", "type": "r", "chg": "none"}, {"dest": "9 - 13", "src": "12 - 17", "type": "r", "chg": "none"}, {"dest": "9 - 13", "src": "13 - 18", "type": "r", "chg": "none"}, {"dest": "9 - 13", "src": "14 - 19", "type": "r", "chg": "none"}, {"dest": "9 - 13", "src": "5 - ", "type": "r", "chg": "del"}, {"dest": "9 - 13", "src": "15 - 9", "type": "r", "chg": "none"}, {"dest": "9 - 13", "src": "16 - 20", "type": "r", "chg": "none"}, {"dest": "9 - 13", "src": "17 - ", "type": "r", "chg": "del"}, {"dest": "9 - 13", "src": "18 - 21", "type": "r", "chg": "none"}, {"dest": "9 - 13", "src": "19 - 22", "type": "r", "chg": "none"}, {"dest": "9 - 13", "src": "20 - 23", "type": "r", "chg": "none"}, {"dest": "21 - 24", "src": "9 - 13", "type": "w", "chg": "none"}, {"dest": "21 - 24", "src": "9 - 13", "type": "rw", "chg": "none"}, {"dest": "3 - 6", "src": "9 - 13", "type": "rw", "chg": "none"}, {"dest": " - 4", "src": "2 - 2", "type": "parent", "chg": "add"}, {"dest": " - 5", "src": " - 4", "type": "w", "chg": "add"}, {"dest": " - 7", "src": "4 - 3", "type": "parent", "chg": "add"}, {"dest": "3 - 6", "src": " - 7", "type": "rw", "chg": "add"}, {"dest": " - 8", "src": " - 7", "type": "parent", "chg": "add"}, {"dest": " - 8", "src": " - 5", "type": "r", "chg": "add"}, {"dest": "15 - 9", "src": " - 8", "type": "w", "chg": "add"}, {"dest": "3 - 6", "src": " - 8", "type": "rw", "chg": "add"}, {"dest": " - 12", "src": "6 - 10", "type": "w", "chg": "none"}, {"dest": "9 - 13", "src": " - 14", "type": "r", "chg": "add"}], "root": "21 - 24"}